[{"fields": {"parse": "Equal@i(RadiusOf@11(Circle@7('O'@8)), [5]@13)", "number": 0, "sentence": 1690}, "model": "semantics.semanticparse", "pk": 13}, {"fields": {"parse": "Equal@17(LengthOf@i(Line@i('CE'@16)), [2]@18)", "number": 1, "sentence": 1690}, "model": "semantics.semanticparse", "pk": 14}, {"fields": {"parse": "Perpendicular@3(Line@i('AC'@1), Line@i('BD'@6))", "number": 0, "sentence": 1691}, "model": "semantics.semanticparse", "pk": 15}, {"fields": {"parse": "IsDiameter@0(Line@i('AC'@1), circle@i)", "number": 1, "sentence": 1691}, "model": "semantics.semanticparse", "pk": 16}, {"fields": {"parse": "IsChord@5(Line@i('BD'@6), circle@i)", "number": 2, "sentence": 1691}, "model": "semantics.semanticparse", "pk": 17}, {"fields": {"parse": "Perpendicular@7(Line@i('AB'@5), Line@i('CD'@10))", "number": 0, "sentence": 1693}, "model": "semantics.semanticparse", "pk": 20}, {"fields": {"parse": "IsDiameter@4(Line@i('AB'@5), Circle@1('O'@2))", "number": 1, "sentence": 1693}, "model": "semantics.semanticparse", "pk": 21}, {"fields": {"parse": "IsChord@9(Line@i('CD'@10), Circle@1('O'@2))", "number": 2, "sentence": 1693}, "model": "semantics.semanticparse", "pk": 22}, {"fields": {"parse": "Equal@2(LengthOf@i(Line@i('CD'@1)), [8]@3)", "number": 0, "sentence": 1694}, "model": "semantics.semanticparse", "pk": 23}, {"fields": {"parse": "Equal@2(LengthOf@i(Line@i('BE'@5)), [2]@7)", "number": 1, "sentence": 1694}, "model": "semantics.semanticparse", "pk": 24}, {"fields": {"parse": "Find@9(LengthOf@i(Line@i('AE'@10)))", "number": 2, "sentence": 1694}, "model": "semantics.semanticparse", "pk": 25}, {"fields": {"parse": "Equal@i(unkNum@0, LengthOf@3(Line@i('BD'@5)))", "number": 0, "sentence": 1692}, "model": "semantics.semanticparse", "pk": 26}, {"fields": {"parse": "BisectsLine@11(line@i, Line@i('AB'@13))", "number": 0, "sentence": 1695}, "model": "semantics.semanticparse", "pk": 27}, {"fields": {"parse": "Perpendicular@10(line@i, Line@i('AB'@13))", "number": 1, "sentence": 1695}, "model": "semantics.semanticparse", "pk": 28}, {"fields": {"parse": "unkSt@0", "number": 0, "sentence": 1696}, "model": "semantics.semanticparse", "pk": 29}, {"fields": {"parse": "Parallel@9(Line@7('PS'@8), Line@11('RQ'@12))", "number": 0, "sentence": 1697}, "model": "semantics.semanticparse", "pk": 30}, {"fields": {"parse": "unkSt@0", "number": 0, "sentence": 1698}, "model": "semantics.semanticparse", "pk": 31}, {"fields": {"parse": "IsMedian@7(Line@i('BF'@8), Triangle@1('ABC'@2))", "number": 0, "sentence": 1699}, "model": "semantics.semanticparse", "pk": 32}, {"fields": {"parse": "IsAltitude@10(Line@i('BD'@11), Triangle@1('ABC'@2))", "number": 1, "sentence": 1699}, "model": "semantics.semanticparse", "pk": 33}, {"fields": {"parse": "BisectsAngle@15(Line@i('BE'@14), Angle@16('ABC'@17))", "number": 2, "sentence": 1699}, "model": "semantics.semanticparse", "pk": 34}, {"fields": {"parse": "unkSt@19", "number": 3, "sentence": 1699}, "model": "semantics.semanticparse", "pk": 35}, {"fields": {"parse": "Tangent@11(Line@7('PS'@8), Circle@13('O'@14))", "number": 0, "sentence": 1700}, "model": "semantics.semanticparse", "pk": 38}, {"fields": {"parse": "Secant@23(Line@19('PQR'@20), circle@i)", "number": 1, "sentence": 1700}, "model": "semantics.semanticparse", "pk": 39}, {"fields": {"parse": "Equal@26(LengthOf@i(Line@i('PS'@25)), <x>@27)", "number": 2, "sentence": 1700}, "model": "semantics.semanticparse", "pk": 40}, {"fields": {"parse": "Equal@30(LengthOf@i(Line@i('PQ'@29)), [3]@31)", "number": 3, "sentence": 1700}, "model": "semantics.semanticparse", "pk": 41}, {"fields": {"parse": "Equal@34(LengthOf@i(Line@i('PR'@33)), Add@36(<x>@35, [18]@37))", "number": 4, "sentence": 1700}, "model": "semantics.semanticparse", "pk": 42}, {"fields": {"parse": "Equal@i(unkNum@0, LengthOf@3(Line@5('PS'@6)))", "number": 0, "sentence": 1701}, "model": "semantics.semanticparse", "pk": 43}, {"fields": {"parse": "Equal@17(LengthOf@i(Line@i('AC'@16)), [7]@18)", "number": 0, "sentence": 1702}, "model": "semantics.semanticparse", "pk": 44}, {"fields": {"parse": "Equal@21(LengthOf@i(Line@i('AD'@20)), [6]@22)", "number": 1, "sentence": 1702}, "model": "semantics.semanticparse", "pk": 45}, {"fields": {"parse": "Equal@26(LengthOf@i(Line@i('BC'@25)), [18]@27)", "number": 2, "sentence": 1702}, "model": "semantics.semanticparse", "pk": 46}, {"fields": {"parse": "Equal@i(LengthOf@1(Line@3('DB'@4)), unkNum@i)", "number": 0, "sentence": 1703}, "model": "semantics.semanticparse", "pk": 47}, {"fields": {"parse": "On@11(Point@10('Q'@7), Line@12('PR'@13))", "number": 0, "sentence": 1704}, "model": "semantics.semanticparse", "pk": 48}, {"fields": {"parse": "On@19(Point@18('S'@15), Line@20('TR'@21))", "number": 1, "sentence": 1704}, "model": "semantics.semanticparse", "pk": 49}, {"fields": {"parse": "Equal@31(AngleOf@i(Angle@29('RPT'@30)), AngleOf@i(Angle@32('RSQ'@33)))", "number": 2, "sentence": 1704}, "model": "semantics.semanticparse", "pk": 50}, {"fields": {"parse": "Parallel@7(Line@4('DE'@5), Line@9('AC'@10))", "number": 0, "sentence": 1708}, "model": "semantics.semanticparse", "pk": 51}, {"fields": {"parse": "Equal@13(LengthOf@i(Line@i('DB'@12)), [4]@14)", "number": 1, "sentence": 1708}, "model": "semantics.semanticparse", "pk": 52}, {"fields": {"parse": "Equal@17(LengthOf@i(Line@i('AD'@16)), [8]@18)", "number": 2, "sentence": 1708}, "model": "semantics.semanticparse", "pk": 53}, {"fields": {"parse": "Equal@22(LengthOf@i(Line@i('DE'@21)), [5]@23)", "number": 3, "sentence": 1708}, "model": "semantics.semanticparse", "pk": 54}, {"fields": {"parse": "Find@0(LengthOf@i(Line@i('AC'@1)))", "number": 0, "sentence": 1709}, "model": "semantics.semanticparse", "pk": 55}, {"fields": {"parse": "IsRhombus@2(Quad@i('PQRS'@3))", "number": 0, "sentence": 1714}, "model": "semantics.semanticparse", "pk": 56}, {"fields": {"parse": "Equal@6(LengthOf@i(Line@i('PR'@5)), [24]@7)", "number": 1, "sentence": 1714}, "model": "semantics.semanticparse", "pk": 57}, {"fields": {"parse": "Equal@10(LengthOf@i(Line@i('QS'@9)), [10]@11)", "number": 2, "sentence": 1714}, "model": "semantics.semanticparse", "pk": 58}, {"fields": {"parse": "Find@0(PerimeterOf@2(Quad@5(the@4)))", "number": 0, "sentence": 1715}, "model": "semantics.semanticparse", "pk": 59}, {"fields": {"parse": "IsSecant@4(Line@i('SD'@5), Circle@1('O'@2))", "number": 0, "sentence": 1716}, "model": "semantics.semanticparse", "pk": 60}, {"fields": {"parse": "IsSecant@12(Line@i('SB'@13), Circle@1('O'@2))", "number": 1, "sentence": 1716}, "model": "semantics.semanticparse", "pk": 61}, {"fields": {"parse": "Equal@2(LengthOf@i(Line@i('SC'@1)), [6]@3)", "number": 0, "sentence": 1717}, "model": "semantics.semanticparse", "pk": 62}, {"fields": {"parse": "Equal@6(LengthOf@i(Line@i('CD'@5)), [8]@7)", "number": 1, "sentence": 1717}, "model": "semantics.semanticparse", "pk": 63}, {"fields": {"parse": "Equal@11(LengthOf@i(Line@i('SA'@10)), [4]@12)", "number": 2, "sentence": 1717}, "model": "semantics.semanticparse", "pk": 64}, {"fields": {"parse": "Find@14(LengthOf@i(Line@i('AB'@15)))", "number": 3, "sentence": 1717}, "model": "semantics.semanticparse", "pk": 65}, {"fields": {"parse": "On@16(Point@15('D'@12), Line@17('BC'@18))", "number": 0, "sentence": 1718}, "model": "semantics.semanticparse", "pk": 66}, {"fields": {"parse": "IsRight@5(Triangle@6('ABC'@7))", "number": 0, "sentence": 1720}, "model": "semantics.semanticparse", "pk": 67}, {"fields": {"parse": "IsAltitude@9(Line@i('AD'@10), Triangle@6('ABC'@7))", "number": 1, "sentence": 1720}, "model": "semantics.semanticparse", "pk": 68}, {"fields": {"parse": "IsHypotenuse@12(Line@i('BC'@13), Triangle@6('ABC'@7))", "number": 2, "sentence": 1720}, "model": "semantics.semanticparse", "pk": 69}, {"fields": {"parse": "Find@0(LengthOf@2(Line@i('AB'@5)))", "number": 0, "sentence": 1721}, "model": "semantics.semanticparse", "pk": 70}, {"fields": {"parse": "Parallel@8(Line@5('AB'@6), Line@10('CD'@11))", "number": 0, "sentence": 1722}, "model": "semantics.semanticparse", "pk": 71}, {"fields": {"parse": "Equal@18(AngleOf@i(Angle@16('AEF'@17)), [40]@19)", "number": 1, "sentence": 1722}, "model": "semantics.semanticparse", "pk": 72}, {"fields": {"parse": "Equal@24(AngleOf@i(Angle@22('FHG'@23)), [60]@25)", "number": 2, "sentence": 1722}, "model": "semantics.semanticparse", "pk": 73}, {"fields": {"parse": "Find@0(AngleOf@i(Angle@1('HGD'@2)))", "number": 0, "sentence": 1723}, "model": "semantics.semanticparse", "pk": 74}, {"fields": {"parse": "Tangent@11(Line@5('PQ'@6), Circle@14('O'@15))", "number": 0, "sentence": 1724}, "model": "semantics.semanticparse", "pk": 75}, {"fields": {"parse": "Tangent@11(Line@8('PS'@9), Circle@14('O'@15))", "number": 1, "sentence": 1724}, "model": "semantics.semanticparse", "pk": 76}, {"fields": {"parse": "IsChord@18(Line@i('QS'@19), circle@i)", "number": 2, "sentence": 1724}, "model": "semantics.semanticparse", "pk": 77}, {"fields": {"parse": "Equal@3(AngleOf@i(Angle@1('P'@2)), [40]@4)", "number": 0, "sentence": 1725}, "model": "semantics.semanticparse", "pk": 78}, {"fields": {"parse": "Equal@i(unkNum@6, AngleOf@i(Angle@8('PQS'@9)))", "number": 1, "sentence": 1725}, "model": "semantics.semanticparse", "pk": 79}, {"fields": {"parse": "Intersects@10(Line@5('AB'@6), Line@8('CD'@9))", "number": 0, "sentence": 1726}, "model": "semantics.semanticparse", "pk": 80}, {"fields": {"parse": "IsMidpoint@17(Point@i('E'@14), Line@19('AB'@20))", "number": 1, "sentence": 1726}, "model": "semantics.semanticparse", "pk": 81}, {"fields": {"parse": "Equilateral@8(Triangle@9('ABC'@5))", "number": 0, "sentence": 1730}, "model": "semantics.semanticparse", "pk": 82}, {"fields": {"parse": "Equal@i(PerimeterOf@12(Triangle@9('ABC'@5)), [30]@14)", "number": 1, "sentence": 1730}, "model": "semantics.semanticparse", "pk": 83}, {"fields": {"parse": "Equal@i(unkNum@0, LengthOf@3(Line@i('h'@6)))", "number": 0, "sentence": 1731}, "model": "semantics.semanticparse", "pk": 84}, {"fields": {"parse": "Tangent@11(Line@8(all@7), Circle@14(the@13))", "number": 0, "sentence": 1735}, "model": "semantics.semanticparse", "pk": 85}, {"fields": {"parse": "Find@0(<x>@4)", "number": 0, "sentence": 1736}, "model": "semantics.semanticparse", "pk": 86}, {"fields": {"parse": "IsDiameter@5(Line@i('CD'@6), Circle@2('O'@3))", "number": 0, "sentence": 1737}, "model": "semantics.semanticparse", "pk": 87}, {"fields": {"parse": "Parallel@2(Line@i('AB'@0), Line@i('CD'@4))", "number": 0, "sentence": 1738}, "model": "semantics.semanticparse", "pk": 88}, {"fields": {"parse": "Equal@8(LengthOf@i(Line@i('AB'@7)), [80]@9)", "number": 1, "sentence": 1738}, "model": "semantics.semanticparse", "pk": 89}, {"fields": {"parse": "Find@0(AngleOfArc@1(Arc@3('CA'@4)))", "number": 0, "sentence": 1739}, "model": "semantics.semanticparse", "pk": 90}, {"fields": {"parse": "Find@0(<x>@5)", "number": 0, "sentence": 1741}, "model": "semantics.semanticparse", "pk": 91}, {"fields": {"parse": "Tangent@5(Line@i('AB'@6), Circle@13('O'@14))", "number": 0, "sentence": 1742}, "model": "semantics.semanticparse", "pk": 92}, {"fields": {"parse": "Secant@8(Line@i('ACD'@9), Circle@13('O'@14))", "number": 1, "sentence": 1742}, "model": "semantics.semanticparse", "pk": 93}, {"fields": {"parse": "Equal@20(LengthOf@i(Line@i('AB'@19)), [6]@21)", "number": 2, "sentence": 1742}, "model": "semantics.semanticparse", "pk": 94}, {"fields": {"parse": "Equal@24(LengthOf@i(Line@i('AC'@23)), [4]@25)", "number": 3, "sentence": 1742}, "model": "semantics.semanticparse", "pk": 95}, {"fields": {"parse": "Find@0(LengthOf@i(Line@i('AD'@1)))", "number": 0, "sentence": 1743}, "model": "semantics.semanticparse", "pk": 96}, {"fields": {"parse": "Secant@7(Line@i('AB'@8), Circle@10('O'@11))", "number": 0, "sentence": 1746}, "model": "semantics.semanticparse", "pk": 97}, {"fields": {"parse": "Secant@15(Line@i('AC'@16), Circle@18('O'@19))", "number": 1, "sentence": 1746}, "model": "semantics.semanticparse", "pk": 98}, {"fields": {"parse": "Equal@24(LengthOf@i(Line@i('AE'@23)), [4]@25)", "number": 2, "sentence": 1746}, "model": "semantics.semanticparse", "pk": 99}, {"fields": {"parse": "Equal@28(LengthOf@i(Line@i('AC'@27)), [24]@29)", "number": 3, "sentence": 1746}, "model": "semantics.semanticparse", "pk": 100}, {"fields": {"parse": "Equal@33(LengthOf@i(Line@i('AC'@32)), [24]@34)", "number": 4, "sentence": 1746}, "model": "semantics.semanticparse", "pk": 101}, {"fields": {"parse": "Find@0(LengthOf@i(Line@i('AD'@1)))", "number": 0, "sentence": 1747}, "model": "semantics.semanticparse", "pk": 102}, {"fields": {"parse": "IsDiameter@7(Line@i('AB'@8), Circle@2(the@1))", "number": 0, "sentence": 1748}, "model": "semantics.semanticparse", "pk": 103}, {"fields": {"parse": "Find@10(<x>@11)", "number": 1, "sentence": 1748}, "model": "semantics.semanticparse", "pk": 104}, {"fields": {"parse": "Find@0(<x>@1)", "number": 0, "sentence": 1750}, "model": "semantics.semanticparse", "pk": 105}, {"fields": {"parse": "Find@12(<x>@21)", "number": 0, "sentence": 1756}, "model": "semantics.semanticparse", "pk": 106}, {"fields": {"parse": "Tangent@1(Line@i('AC'@2), Circle@5(the@4))", "number": 0, "sentence": 1757}, "model": "semantics.semanticparse", "pk": 107}, {"fields": {"parse": "Find@0(<x>@8)", "number": 0, "sentence": 1758}, "model": "semantics.semanticparse", "pk": 108}, {"fields": {"parse": "Find@0(<x>@8)", "number": 0, "sentence": 1760}, "model": "semantics.semanticparse", "pk": 109}, {"fields": {"parse": "Find@0(<x>@8)", "number": 0, "sentence": 1762}, "model": "semantics.semanticparse", "pk": 110}, {"fields": {"parse": "Tangent@8(Line@i(all@i), Circle@11(the@10))", "number": 0, "sentence": 1763}, "model": "semantics.semanticparse", "pk": 111}, {"fields": {"parse": "Find@0(<x>@8)", "number": 0, "sentence": 1764}, "model": "semantics.semanticparse", "pk": 112}, {"fields": {"parse": "Equal@4(LengthOf@i(Line@2('AB'@3)), LengthOf@i(Line@5('AC'@6)))", "number": 0, "sentence": 1765}, "model": "semantics.semanticparse", "pk": 113}, {"fields": {"parse": "Equal@i(RadiusOf@14(Circle@2(the@1)), [5]@15)", "number": 0, "sentence": 1767}, "model": "semantics.semanticparse", "pk": 114}, {"fields": {"parse": "Equal@9(LengthOf@i(Line@7('AC'@8)), LengthOf@i(Line@10('DC'@11)))", "number": 0, "sentence": 1773}, "model": "semantics.semanticparse", "pk": 115}, {"fields": {"parse": "Equal@12(LengthOf@i(Line@10('DC'@11)), LengthOf@i(Line@13('DB'@14)))", "number": 1, "sentence": 1773}, "model": "semantics.semanticparse", "pk": 116}, {"fields": {"parse": "Equal@4(AngleOf@i(Angle@2('ACD'@3)), [48]@5)", "number": 0, "sentence": 1774}, "model": "semantics.semanticparse", "pk": 117}, {"fields": {"parse": "Find@7(AngleOf@i(Angle@9('B'@10)))", "number": 1, "sentence": 1774}, "model": "semantics.semanticparse", "pk": 118}, {"fields": {"parse": "IsRight@7(Triangle@8(the@6))", "number": 0, "sentence": 1775}, "model": "semantics.semanticparse", "pk": 119}, {"fields": {"parse": "Equal@i(unkNum@0, <x>@5)", "number": 0, "sentence": 1776}, "model": "semantics.semanticparse", "pk": 120}, {"fields": {"parse": "Equal@7(LengthOf@i(Line@5('BA'@6)), LengthOf@i(Line@8('BC'@9)))", "number": 0, "sentence": 1777}, "model": "semantics.semanticparse", "pk": 121}, {"fields": {"parse": "Equal@13(<x>@12, [117]@14)", "number": 1, "sentence": 1777}, "model": "semantics.semanticparse", "pk": 122}, {"fields": {"parse": "Find@0(<y>@2)", "number": 0, "sentence": 1778}, "model": "semantics.semanticparse", "pk": 123}, {"fields": {"parse": "Find@0(AngleOf@i(Angle@2('DBC'@3)))", "number": 0, "sentence": 1780}, "model": "semantics.semanticparse", "pk": 124}, {"fields": {"parse": "Equal@3(LengthOf@i(Line@1('AB'@2)), LengthOf@i(Line@4('DE'@5)))", "number": 0, "sentence": 1781}, "model": "semantics.semanticparse", "pk": 125}, {"fields": {"parse": "Equal@9(AngleOf@i(Angle@7('A'@8)), AngleOf@i(Angle@10('D'@11)))", "number": 1, "sentence": 1781}, "model": "semantics.semanticparse", "pk": 126}, {"fields": {"parse": "Find@0(<x>@1)", "number": 0, "sentence": 1783}, "model": "semantics.semanticparse", "pk": 127}, {"fields": {"parse": "IsMidpoint@10(Point@0('A'@1), Line@13(the@12))", "number": 0, "sentence": 1786}, "model": "semantics.semanticparse", "pk": 128}, {"fields": {"parse": "IsMidpoint@10(Point@0('B'@3), Line@13(the@12))", "number": 1, "sentence": 1786}, "model": "semantics.semanticparse", "pk": 129}, {"fields": {"parse": "IsMidpoint@10(Point@0('C'@5), Line@13(the@12))", "number": 2, "sentence": 1786}, "model": "semantics.semanticparse", "pk": 130}, {"fields": {"parse": "Equal@i(AreaOf@2(Quad@i('JETS'@4)), [36]@6)", "number": 0, "sentence": 1787}, "model": "semantics.semanticparse", "pk": 131}, {"fields": {"parse": "Equal@i(AreaOf@9(Quad@i('ABCD'@11)), unkNum@i)", "number": 1, "sentence": 1787}, "model": "semantics.semanticparse", "pk": 132}, {"fields": {"parse": "Equal@10(AngleOf@i(Angle@8('ABE'@9)), [30]@11)", "number": 0, "sentence": 1792}, "model": "semantics.semanticparse", "pk": 133}, {"fields": {"parse": "Equal@15(AngleOf@i(Angle@13('CFE'@14)), [144]@16)", "number": 1, "sentence": 1792}, "model": "semantics.semanticparse", "pk": 134}, {"fields": {"parse": "Find@0(AngleOf@i(Angle@1('BEF'@2)))", "number": 0, "sentence": 1793}, "model": "semantics.semanticparse", "pk": 135}, {"fields": {"parse": "Parallel@10(Line@7('a'@8), Line@12('b'@13))", "number": 0, "sentence": 1796}, "model": "semantics.semanticparse", "pk": 136}, {"fields": {"parse": "IsSquare@10(Quad@i('ABCD'@7))", "number": 0, "sentence": 1801}, "model": "semantics.semanticparse", "pk": 137}, {"fields": {"parse": "Equal@23(LengthOf@i(Line@21('AD'@22)), LengthOf@i(Line@24('DE'@25)))", "number": 1, "sentence": 1801}, "model": "semantics.semanticparse", "pk": 138}, {"fields": {"parse": "Equal@i(unkNum@0, AngleOf@i(Angle@2('DAE'@3)))", "number": 0, "sentence": 1802}, "model": "semantics.semanticparse", "pk": 139}, {"fields": {"parse": "IsRhombus@5(Quad@i('ABCD'@6))", "number": 0, "sentence": 1803}, "model": "semantics.semanticparse", "pk": 140}, {"fields": {"parse": "Equal@10(AngleOf@i(Angle@8('CAB'@9)), [35]@11)", "number": 1, "sentence": 1803}, "model": "semantics.semanticparse", "pk": 141}, {"fields": {"parse": "Find@0(AngleOf@i(Angle@1('CDA'@2)))", "number": 0, "sentence": 1804}, "model": "semantics.semanticparse", "pk": 142}, {"fields": {"parse": "Equal@6(LengthOf@i(Line@i('AD'@5)), [4]@7)", "number": 0, "sentence": 1805}, "model": "semantics.semanticparse", "pk": 143}, {"fields": {"parse": "Equal@10(LengthOf@i(Line@i('AB'@9)), [3]@11)", "number": 1, "sentence": 1805}, "model": "semantics.semanticparse", "pk": 144}, {"fields": {"parse": "Equal@14(LengthOf@i(Line@i('CD'@13)), [9]@15)", "number": 2, "sentence": 1805}, "model": "semantics.semanticparse", "pk": 145}, {"fields": {"parse": "Equal@i(unkNum@0, AreaOf@3(Triangle@5('AEC'@6)))", "number": 0, "sentence": 1806}, "model": "semantics.semanticparse", "pk": 146}, {"fields": {"parse": "Equal@i(unkNum@0, <x>@9)", "number": 0, "sentence": 1807}, "model": "semantics.semanticparse", "pk": 147}, {"fields": {"parse": "IsSquare@5(quad@i)", "number": 0, "sentence": 1815}, "model": "semantics.semanticparse", "pk": 148}, {"fields": {"parse": "Tangent@11(Line@8(all@i), circle@14(the@13))", "number": 1, "sentence": 1815}, "model": "semantics.semanticparse", "pk": 149}, {"fields": {"parse": "IsParallelogram@3(Quad@i('PQRS'@0))", "number": 0, "sentence": 1817}, "model": "semantics.semanticparse", "pk": 150}, {"fields": {"parse": "Equal@6(LengthOf@i(Line@i('ST'@5)), LengthOf@i(Line@i('TR'@7)))", "number": 1, "sentence": 1817}, "model": "semantics.semanticparse", "pk": 151}, {"fields": {"parse": "Equal@5(LengthOf@i(Line@i('AD'@4)), LengthOf@i(Line@i('DB'@6)))", "number": 0, "sentence": 1826}, "model": "semantics.semanticparse", "pk": 152}, {"fields": {"parse": "Parallel@10(Line@i('DE'@8), Line@i('BC'@12))", "number": 1, "sentence": 1826}, "model": "semantics.semanticparse", "pk": 153}, {"fields": {"parse": "Equal@i(AreaOf@16(Triangle@18('ABC'@19)), [40]@21)", "number": 2, "sentence": 1826}, "model": "semantics.semanticparse", "pk": 154}, {"fields": {"parse": "Equal@i(unkNum@0, AreaOf@3(Triangle@5('ADE'@6)))", "number": 0, "sentence": 1827}, "model": "semantics.semanticparse", "pk": 155}]